cfundata2/__init__.py
cfundata2/frequency.parquet
cfundata2/frequency2.parquet
cfundata2-0.2.2.dist-info/METADATA
cfundata2-0.2.2.dist-info/WHEEL
cfundata2-0.2.2.dist-info/entry_points.txt
cfundata2-0.2.2.dist-info/RECORD
