Metadata-Version: 2.4
Name: cfundata2
Version: 0.2.2
Summary: my data
Author-email: zoushucai <zoushucai@users.noreply.github.com>
Requires-Python: >=3.10
